<?xml version = '1.0' encoding = 'UTF-8'?>
<Relation class="oracle.dbtools.crest.model.design.logical.Relation" name="Relation_11" directorySegmentName="seg_0" id="69ACE864-FE49-797B-D267-16C4A47414B7">
<createdBy>Korisnik</createdBy>
<createdTime>2023-04-26 01:27:16 UTC</createdTime>
<ownerDesignName>TRG_Reservations</ownerDesignName>
<engineerTo>
<item key="0652E0C5-94DC-D48F-55FF-2D7FE81777CC" value="true"/>
</engineerTo>
<sourcePk>F6D02E79-4A4E-C573-B442-6DCF36FFE8D7</sourcePk>
<identifying>false</identifying>
<optionalSource>true</optionalSource>
<optionalTarget>false</optionalTarget>
<sourceCardinality>1</sourceCardinality>
<sourceEntity>1D83B329-FA27-E56F-5808-ADC01B78BCCB</sourceEntity>
<targetCardinalityString>*</targetCardinalityString>
<targetEntity>91A1B17D-55A0-80C2-48D5-2805B82E13D9</targetEntity>
<transferable>true</transferable>
<deleteRule>NO ACTION</deleteRule>
</Relation>
